{"chunk_definitions":[{"row":40,"row_count":1,"visible":true,"expansion_state":0,"options":{"engine":"r","label":"setup","include":false,"dev":"png"},"document_id":"C0DBD1CA","chunk_id":"csetup_chunk","chunk_label":"setup"},{"row":82,"row_count":1,"visible":true,"expansion_state":0,"options":{"engine":"r","label":"load-data","dev":"png"},"document_id":"C0DBD1CA","chunk_id":"cg18owjw74e2g","chunk_label":"load-data"},{"row":106,"row_count":1,"visible":true,"expansion_state":0,"options":{"engine":"r","label":"split","dev":"png"},"document_id":"C0DBD1CA","chunk_id":"ctyjgrxc3vawo","chunk_label":"split"},{"row":121,"row_count":1,"visible":true,"expansion_state":0,"options":{"engine":"r","label":"check-balance","dev":"png"},"document_id":"C0DBD1CA","chunk_id":"ch6j0iri6h8h4","chunk_label":"check-balance"},{"row":146,"row_count":1,"visible":true,"expansion_state":0,"options":{"engine":"r","label":"plot-spectra","fig.cap":"Log-périodogramme moyen par phonème","dev":"png"},"document_id":"C0DBD1CA","chunk_id":"cwul0fyfqoyub","chunk_label":"plot-spectra"},{"row":164,"row_count":1,"visible":true,"expansion_state":0,"options":{},"document_id":"C0DBD1CA","chunk_id":"cqrs846pxnv2q","chunk_label":"pca"},{"row":219,"row_count":1,"visible":true,"expansion_state":0,"options":{},"document_id":"C0DBD1CA","chunk_id":"c3t695up9wahu","chunk_label":"cah"},{"row":228,"row_count":1,"visible":true,"expansion_state":0,"options":{},"document_id":"C0DBD1CA","chunk_id":"cfli6neyejwd1","chunk_label":"cah-cross"},{"row":241,"row_count":1,"visible":true,"expansion_state":0,"options":{},"document_id":"C0DBD1CA","chunk_id":"cn9pzawoyg4rf","chunk_label":"cah-visu"},{"row":253,"row_count":1,"visible":true,"expansion_state":0,"options":{},"document_id":"C0DBD1CA","chunk_id":"cxztpb5ayk2em","chunk_label":"kmeans"},{"row":264,"row_count":1,"visible":true,"expansion_state":0,"options":{},"document_id":"C0DBD1CA","chunk_id":"cnn9cp0w0z71z","chunk_label":"purity"},{"row":277,"row_count":1,"visible":true,"expansion_state":0,"options":{},"document_id":"C0DBD1CA","chunk_id":"c9co0de6htn5m","chunk_label":"plsda-init"},{"row":288,"row_count":1,"visible":true,"expansion_state":0,"options":{},"document_id":"C0DBD1CA","chunk_id":"cjmylmlpbffyd","chunk_label":"plsda-perf"},{"row":295,"row_count":1,"visible":true,"expansion_state":0,"options":{},"document_id":"C0DBD1CA","chunk_id":"cm4zvx7eurasl","chunk_label":"plsda-perf-plot"},{"row":305,"row_count":1,"visible":true,"expansion_state":0,"options":{},"document_id":"C0DBD1CA","chunk_id":"c5cm67wbsjfkh","chunk_label":"plsda-ncomp"},{"row":313,"row_count":1,"visible":true,"expansion_state":0,"options":{},"document_id":"C0DBD1CA","chunk_id":"c6sao6hcfad47","chunk_label":"plsda-final"},{"row":330,"row_count":1,"visible":true,"expansion_state":0,"options":{},"document_id":"C0DBD1CA","chunk_id":"ct8ut2uvnzlcd","chunk_label":"plsda-indiv"},{"row":345,"row_count":1,"visible":true,"expansion_state":0,"options":{},"document_id":"C0DBD1CA","chunk_id":"cbt5dctair5c6","chunk_label":"plsda-indiv34"},{"row":354,"row_count":1,"visible":true,"expansion_state":0,"options":{},"document_id":"C0DBD1CA","chunk_id":"cbkiffet1xqzz","chunk_label":"plsda-var"},{"row":377,"row_count":1,"visible":true,"expansion_state":0,"options":{},"document_id":"C0DBD1CA","chunk_id":"cfhmemain9mbp","chunk_label":"plsda-vip"},{"row":384,"row_count":1,"visible":true,"expansion_state":0,"options":{},"document_id":"C0DBD1CA","chunk_id":"chm15glo2qg9v","chunk_label":"vip-summary"},{"row":405,"row_count":1,"visible":true,"expansion_state":0,"options":{},"document_id":"C0DBD1CA","chunk_id":"ce0trg8d7ezo9","chunk_label":"splsda"},{"row":419,"row_count":1,"visible":true,"expansion_state":0,"options":{},"document_id":"C0DBD1CA","chunk_id":"cl2im5ahc6m6j","chunk_label":"splsda-indiv"},{"row":435,"row_count":1,"visible":true,"expansion_state":0,"options":{},"document_id":"C0DBD1CA","chunk_id":"c7fv1hvxy6hte","chunk_label":"eval-test"},{"row":443,"row_count":1,"visible":true,"expansion_state":0,"options":{},"document_id":"C0DBD1CA","chunk_id":"cr31qkc53y0y1","chunk_label":"cm-plsda"},{"row":451,"row_count":1,"visible":true,"expansion_state":0,"options":{},"document_id":"C0DBD1CA","chunk_id":"ctbnus22itk6v","chunk_label":"cm-splsda"},{"row":471,"row_count":1,"visible":true,"expansion_state":0,"options":{},"document_id":"C0DBD1CA","chunk_id":"catgtviav3qhh","chunk_label":"perf-tab"},{"row":491,"row_count":1,"visible":true,"expansion_state":0,"options":{},"document_id":"C0DBD1CA","chunk_id":"cxsswpo592bvn","chunk_label":"perf-global"},{"row":498,"row_count":1,"visible":true,"expansion_state":0,"options":{},"document_id":"C0DBD1CA","chunk_id":"caoymtcim60jn","chunk_label":"auc"},{"row":534,"row_count":1,"visible":true,"expansion_state":0,"options":{},"document_id":"C0DBD1CA","chunk_id":"c46461rtdn73l","chunk_label":"final-summary"}],"doc_write_time":1773907295,"working_dir":null,"default_chunk_options":{}}